odoo8_addon_crm_claim_code-8.0.1.0.0.99.dev15-py2.7-nspkg.pth
odoo8_addon_crm_claim_code-8.0.1.0.0.99.dev15.dist-info/METADATA
odoo8_addon_crm_claim_code-8.0.1.0.0.99.dev15.dist-info/RECORD
odoo8_addon_crm_claim_code-8.0.1.0.0.99.dev15.dist-info/WHEEL
odoo8_addon_crm_claim_code-8.0.1.0.0.99.dev15.dist-info/namespace_packages.txt
odoo8_addon_crm_claim_code-8.0.1.0.0.99.dev15.dist-info/top_level.txt
odoo_addons/crm_claim_code/README.rst
odoo_addons/crm_claim_code/__init__.py
odoo_addons/crm_claim_code/__openerp__.py
odoo_addons/crm_claim_code/data/claim_sequence.xml
odoo_addons/crm_claim_code/i18n/bg.po
odoo_addons/crm_claim_code/i18n/crm_claim_code.pot
odoo_addons/crm_claim_code/i18n/de.po
odoo_addons/crm_claim_code/i18n/es.po
odoo_addons/crm_claim_code/i18n/es_MX.po
odoo_addons/crm_claim_code/i18n/es_VE.po
odoo_addons/crm_claim_code/i18n/fr.po
odoo_addons/crm_claim_code/i18n/hr.po
odoo_addons/crm_claim_code/i18n/it.po
odoo_addons/crm_claim_code/i18n/nb.po
odoo_addons/crm_claim_code/i18n/pt_BR.po
odoo_addons/crm_claim_code/i18n/sk.po
odoo_addons/crm_claim_code/i18n/sl.po
odoo_addons/crm_claim_code/i18n/sv.po
odoo_addons/crm_claim_code/models/__init__.py
odoo_addons/crm_claim_code/models/crm_claim.py
odoo_addons/crm_claim_code/static/description/icon.png
odoo_addons/crm_claim_code/tests/__init__.py
odoo_addons/crm_claim_code/tests/test_crm_claim_code.py
odoo_addons/crm_claim_code/views/crm_claim_view.xml
